puflib/VERSION_STAMP
puflib/__init__.py
puflib/architectures.py
puflib/test.py
puflib/util.py
puflib/version.py
puflib-0.2.14.dist-info/LICENSE
puflib-0.2.14.dist-info/METADATA
puflib-0.2.14.dist-info/WHEEL
puflib-0.2.14.dist-info/top_level.txt
puflib-0.2.14.dist-info/RECORD
